[
    {
        "id": 1,
        "word": "unfavourably",
        "translation": "不利的，不受欢迎的,不容乐观的",
        "tags": [
            "六级真题记录"
        ]
    },
    {
        "id": 2,
        "word": "in terms of",
        "translation": "就...而言",
        "tags": [
            "六级真题记录"
        ]
    },
    {
        "id": 3,
        "word": "urge",
        "translation": "敦促",
        "tags": [
            "六级真题记录"
        ]
    },
    {
        "id": 4,
        "word": "bend on doing sth",
        "translation": "致力于做某事,决心做某事",
        "tags": [
            "六级真题记录"
        ]
    },
    {
        "id": 5,
        "word": "Republicans",
        "translation": "共和党人",
        "tags": [
            "六级真题记录"
        ]
    },
    {
        "id": 6,
        "word": "Democrats",
        "translation": "民主党人",
        "tags": [
            "六级真题记录"
        ]
    },
    {
        "id": 7,
        "word": "affiliation",
        "translation": "隶属,从属,归属感",
        "tags": [
            "六级真题记录"
        ]
    },
    {
        "id": 8,
        "word": "indeed",
        "translation": "确实,真正地",
        "tags": [
            "六级真题记录"
        ]
    },
    {
        "id": 9,
        "word": "a handful of",
        "translation": "一把,一撮,少数",
        "tags": [
            "六级真题记录"
        ]
    },
    {
        "id": 10,
        "word": "static",
        "translation": "静态的,静止的,固定的",
        "tags": [
            "六级真题记录"
        ]
    },
    {
        "id": 11,
        "word": "crucial",
        "translation": "至关重要的,决定性的",
        "tags": [
            "六级真题记录"
        ]
    },
    {
        "id": 12,
        "word": "compel",
        "translation": "强迫,迫使",
        "tags": [
            "六级真题记录"
        ]
    },
    {
        "id": 13,
        "word": "render",
        "translation": "呈现,描绘,表演",
        "tags": [
            "六级真题记录"
        ]
    },
    {
        "id": 14,
        "word": "overrule",
        "translation": "否决,驳回,压制",
        "tags": [
            "六级真题记录"
        ]
    },
    {
        "id": 15,
        "word": "assertive",
        "translation": "自信的，断言的",
        "tags": [
            "六级真题记录"
        ]
    },
    {
        "id": 16,
        "word": "esteemed",
        "translation": "受尊敬的,值得尊敬的",
        "tags": [
            "六级真题记录"
        ]
    },
    {
        "id": 17,
        "word": "esteem",
        "translation": "尊敬,尊重",
        "tags": [
            "六级真题记录"
        ]
    },
    {
        "id": 18,
        "word": "envolve",
        "translation": "进化",
        "tags": [
            "六级真题记录"
        ]
    },
    {
        "id": 19,
        "word": "passage",
        "translation": "推移，the passage of time随着时间推移",
        "tags": [
            "六级真题记录"
        ]
    },
    {
        "id": 20,
        "word": "perception",
        "translation": "知觉",
        "tags": [
            "六级真题记录"
        ]
    },
    {
        "id": 21,
        "word": "self-discipline",
        "translation": "自律",
        "tags": [
            "六级真题记录"
        ]
    },
    {
        "id": 22,
        "word": "consciously",
        "translation": "自觉",
        "tags": [
            "六级真题记录"
        ]
    }
]